get_resource_path/GetResourcePath.py
get_resource_path/__init__.py
GetResourcePath-1.0.dist-info/LICENSE.txt
GetResourcePath-1.0.dist-info/METADATA
GetResourcePath-1.0.dist-info/WHEEL
GetResourcePath-1.0.dist-info/top_level.txt
GetResourcePath-1.0.dist-info/RECORD
