Metadata-Version: 2.1
Name: GetResourcePath
Version: 1.0
Summary: A Python package for managing resource paths and file operations in cross-platform applications.
Home-page: https://github.com/jjvoka/getpath
Author: voka
Author-email: jjvoka@gmail.com
License-File: LICENSE.txt
